cache_result/__init__.py
cache_result-0.2.6.dist-info/METADATA
cache_result-0.2.6.dist-info/WHEEL
cache_result-0.2.6.dist-info/top_level.txt
cache_result-0.2.6.dist-info/RECORD
