Metadata-Version: 2.1
Name: cache-result
Version: 0.2.6
Summary: A python decorator for caching the results of functions
Author: glwhappen
Author-email: 1597721684@qq.com
Project-URL: Source Code, https://github.com/glwhappen/cache-result
Requires-Dist: colorama
Requires-Dist: loguru
